cubicweb_leaflet/__init__.py
cubicweb_leaflet/__pkginfo__.py
cubicweb_leaflet/uiprops.py
cubicweb_leaflet/views.py
cubicweb_leaflet/data/cubes.leaflet.css
cubicweb_leaflet/data/cubes.leaflet.js
cubicweb_leaflet/data/leaflet.css
cubicweb_leaflet/data/leaflet.js
cubicweb_leaflet/data/images/layers-2x.png
cubicweb_leaflet/data/images/layers.png
cubicweb_leaflet/data/images/marker-blue-icon.png
cubicweb_leaflet/data/images/marker-green-icon.png
cubicweb_leaflet/data/images/marker-icon-2x.png
cubicweb_leaflet/data/images/marker-icon.png
cubicweb_leaflet/data/images/marker-red-icon.png
cubicweb_leaflet/data/images/marker-shadow.png
cubicweb_leaflet/data/leafletcluster/MarkerCluster.Default.css
cubicweb_leaflet/data/leafletcluster/MarkerCluster.Default.ie.css
cubicweb_leaflet/data/leafletcluster/MarkerCluster.css
cubicweb_leaflet/data/leafletcluster/leaflet.markercluster-src.js
cubicweb_leaflet/data/leafletcluster/leaflet.markercluster.js
cubicweb_leaflet-1.0.0.dist-info/METADATA
cubicweb_leaflet-1.0.0.dist-info/WHEEL
cubicweb_leaflet-1.0.0.dist-info/entry_points.txt
cubicweb_leaflet-1.0.0.dist-info/top_level.txt
cubicweb_leaflet-1.0.0.dist-info/RECORD
